torchcolor/__init__.py
torchcolor/color.py
torchcolor/gradient.py
torchcolor/palette.py
torchcolor/print.py
torchcolor/printer.py
torchcolor/strategy.py
torchcolor/style.py
torchcolor-0.1.0.dist-info/LICENSE
torchcolor-0.1.0.dist-info/METADATA
torchcolor-0.1.0.dist-info/WHEEL
torchcolor-0.1.0.dist-info/top_level.txt
torchcolor-0.1.0.dist-info/RECORD
