Metadata-Version: 2.1
Name: torchcolor
Version: 0.1.0
Summary: A lightweight Python package for PyTorch that enhances readability by color-coding module prints based on their trainable status.
Author-email: Antoine Debouchage <antoine311200@gmail.com>
License: MIT
Project-URL: Homepage, https://github.com/antoine311200/torchcolor
Project-URL: Issues, https://github.com/antoine311200/torchcolor/issues
Classifier: Programming Language :: Python :: 3
Classifier: License :: OSI Approved :: MIT License
Classifier: Operating System :: OS Independent
License-File: LICENSE
Provides-Extra: torch
Requires-Dist: torch; extra == "torch"
